azure/schemaregistry/__init__.py
azure/schemaregistry/_client.py
azure/schemaregistry/_configuration.py
azure/schemaregistry/_model_base.py
azure/schemaregistry/_patch.py
azure/schemaregistry/_serialization.py
azure/schemaregistry/_types.py
azure/schemaregistry/_vendor.py
azure/schemaregistry/_version.py
azure/schemaregistry/py.typed
azure/schemaregistry/_operations/__init__.py
azure/schemaregistry/_operations/_operations.py
azure/schemaregistry/_operations/_patch.py
azure/schemaregistry/aio/__init__.py
azure/schemaregistry/aio/_client.py
azure/schemaregistry/aio/_configuration.py
azure/schemaregistry/aio/_patch.py
azure/schemaregistry/aio/_vendor.py
azure/schemaregistry/aio/_operations/__init__.py
azure/schemaregistry/aio/_operations/_operations.py
azure/schemaregistry/aio/_operations/_patch.py
azure/schemaregistry/encoder/__init__.py
azure/schemaregistry/encoder/jsonencoder/__init__.py
azure/schemaregistry/encoder/jsonencoder/_constants.py
azure/schemaregistry/encoder/jsonencoder/_exceptions.py
azure/schemaregistry/encoder/jsonencoder/_schema_registry_json_encoder.py
azure/schemaregistry/encoder/jsonencoder/_utils.py
azure/schemaregistry/encoder/jsonencoder/_version.py
azure/schemaregistry/encoder/jsonencoder/py.typed
azure/schemaregistry/encoder/jsonencoder/aio/__init__.py
azure/schemaregistry/encoder/jsonencoder/aio/_async_lru.py
azure/schemaregistry/encoder/jsonencoder/aio/_schema_registry_json_encoder_async.py
azure/schemaregistry/models/__init__.py
azure/schemaregistry/models/_enums.py
azure/schemaregistry/models/_patch.py
azure_schemaregistry-1.3.0.dist-info/LICENSE
azure_schemaregistry-1.3.0.dist-info/METADATA
azure_schemaregistry-1.3.0.dist-info/WHEEL
azure_schemaregistry-1.3.0.dist-info/top_level.txt
azure_schemaregistry-1.3.0.dist-info/RECORD
