Metadata-Version: 2.1
Name: azure-schemaregistry
Version: 1.3.0
Summary: Microsoft Azure Azure Schema Registry Client Library for Python
Home-page: https://github.com/Azure/azure-sdk-for-python
Author: Microsoft Corporation
Author-email: azpysdkhelp@microsoft.com
License: MIT License
Keywords: azure,azure sdk
Classifier: Development Status :: 5 - Production/Stable
Classifier: Programming Language :: Python
Classifier: Programming Language :: Python :: 3 :: Only
Classifier: Programming Language :: Python :: 3
Classifier: Programming Language :: Python :: 3.8
Classifier: Programming Language :: Python :: 3.9
Classifier: Programming Language :: Python :: 3.10
Classifier: Programming Language :: Python :: 3.11
Classifier: Programming Language :: Python :: 3.12
Classifier: License :: OSI Approved :: MIT License
Requires-Python: >=3.8
License-File: LICENSE
Requires-Dist: azure-core <2.0.0,>=1.28.0
Requires-Dist: isodate >=0.6.0
Requires-Dist: typing-extensions >=4.6.0
Provides-Extra: jsonencoder
Requires-Dist: jsonschema >=4.10.3 ; extra == 'jsonencoder'
